prettyAnything/prettyDatabricks.py
prettyAnything-0.0.1.dist-info/LICENCE
prettyAnything-0.0.1.dist-info/METADATA
prettyAnything-0.0.1.dist-info/WHEEL
prettyAnything-0.0.1.dist-info/top_level.txt
prettyAnything-0.0.1.dist-info/RECORD
