Metadata-Version: 2.1
Name: prettyAnything
Version: 0.0.1
Summary: prettyAnything provides you the compatibility to prettify everything with Python
Author-email: broData <niladridasgit@gmail.com>
Project-URL: Homepage, https://github.com/niladridasgit/prettyAnything
Project-URL: Issues, https://github.com/niladridasgit/prettyAnything/issues
License-File: LICENCE
